[
  {
    "time": "163212",
    "data": {
      "sno": "500109047",
      "sna": "YouBike2.0_桃源國中",
      "sarea": "北投區",
      "mday": "2025-04-19 20:20:04",
      "ar": "中央北路四段32號(旁)",
      "sareaen": "Beitou Dist",
      "snaen": "YouBike2.0_Taoyuan Junior High School",
      "aren": "No. 32， Sec.4， Zhongyang Rd. (Side)",
      "act": "1",
      "srcUpdateTime": "2025-04-20 00:31:20",
      "updateTime": "2025-04-20 00:31:26",
      "infoTime": "2025-04-19 20:20:04",
      "infoDate": "2025-04-19",
      "total": 22,
      "available_rent_bikes": 10,
      "latitude": 25.13485,
      "longitude": 121.47769,
      "available_return_bikes": 12
    }
  }
]