[
  {
    "time": "163212",
    "data": {
      "sno": "500106108",
      "sna": "YouBike2.0_中華南海路口",
      "sarea": "中正區",
      "mday": "2025-04-19 22:40:04",
      "ar": "中華路二段343號前",
      "sareaen": "Zhongzheng Dist",
      "snaen": "YouBike2.0_Zhonghua Rd. & Nanhai Rd. Intersection",
      "aren": "No. 343， Sec. 2， Zhonghua Rd.",
      "act": "1",
      "srcUpdateTime": "2025-04-20 00:31:20",
      "updateTime": "2025-04-20 00:31:26",
      "infoTime": "2025-04-19 22:40:04",
      "infoDate": "2025-04-19",
      "total": 15,
      "available_rent_bikes": 7,
      "latitude": 25.02703,
      "longitude": 121.50686,
      "available_return_bikes": 8
    }
  }
]