[
  {
    "time": "163212",
    "data": {
      "sno": "500106075",
      "sna": "YouBike2.0_金山信義路口",
      "sarea": "中正區",
      "mday": "2025-04-19 23:10:03",
      "ar": "金山南路一段148號前側",
      "sareaen": "Zhongzheng Dist",
      "snaen": "YouBike2.0_Jinshan Rd. & Xinyi Rd. Intersection",
      "aren": "No. 148， Sec. 1， Jinshan S. Rd.",
      "act": "1",
      "srcUpdateTime": "2025-04-20 00:31:20",
      "updateTime": "2025-04-20 00:31:26",
      "infoTime": "2025-04-19 23:10:03",
      "infoDate": "2025-04-19",
      "total": 25,
      "available_rent_bikes": 10,
      "latitude": 25.03443,
      "longitude": 121.52721,
      "available_return_bikes": 14
    }
  }
]