[
  {
    "time": "163212",
    "data": {
      "sno": "500107052",
      "sna": "YouBike2.0_松江路431巷口",
      "sarea": "中山區",
      "mday": "2025-04-19 22:26:02",
      "ar": "松江路433號前",
      "sareaen": "Zhongshan Dist",
      "snaen": "YouBike2.0_Ln. 431， Songshan Rd. Intersection",
      "aren": "No. 433， Songjiang Rd.",
      "act": "1",
      "srcUpdateTime": "2025-04-20 00:31:20",
      "updateTime": "2025-04-20 00:31:26",
      "infoTime": "2025-04-19 22:26:02",
      "infoDate": "2025-04-19",
      "total": 15,
      "available_rent_bikes": 12,
      "latitude": 25.06585,
      "longitude": 121.53338,
      "available_return_bikes": 3
    }
  }
]