[
  {
    "time": "161549",
    "data": {
      "sno": "500110059",
      "sna": "YouBike2.0_臺北田徑場(北寧路側)",
      "sarea": "松山區",
      "mday": "2025-04-19 22:42:14",
      "ar": "八德路三段25號前",
      "sareaen": "Songshan Dist",
      "snaen": "YouBike2.0_Taipei Stadium (Beining Rd.)",
      "aren": "No. 25， Sec. 3， Bade Rd.",
      "act": "1",
      "srcUpdateTime": "2025-04-20 00:14:19",
      "updateTime": "2025-04-20 00:14:26",
      "infoTime": "2025-04-19 22:42:14",
      "infoDate": "2025-04-19",
      "total": 37,
      "available_rent_bikes": 1,
      "latitude": 25.04954,
      "longitude": 121.55261,
      "available_return_bikes": 35
    }
  }
]