[
  {
    "time": "161549",
    "data": {
      "sno": "500105085",
      "sna": "YouBike2.0_木新公園",
      "sarea": "文山區",
      "mday": "2025-04-19 23:05:15",
      "ar": "木新路三段278巷11號斜對面",
      "sareaen": "Wenshan Dist",
      "snaen": "YouBike2.0_Mu Sin Park",
      "aren": "No. 11， Ln. 278， Sec. 3， Muxin Rd. (Opposite)",
      "act": "1",
      "srcUpdateTime": "2025-04-20 00:14:19",
      "updateTime": "2025-04-20 00:14:26",
      "infoTime": "2025-04-19 23:05:15",
      "infoDate": "2025-04-19",
      "total": 12,
      "available_rent_bikes": 6,
      "latitude": 24.98217,
      "longitude": 121.55782,
      "available_return_bikes": 6
    }
  }
]