[
  {
    "time": "163212",
    "data": {
      "sno": "500105007",
      "sna": "YouBike2.0_捷運景美站(2號出口)",
      "sarea": "文山區",
      "mday": "2025-04-19 22:42:14",
      "ar": "景文街1號(對面)",
      "sareaen": "Wenshan Dist",
      "snaen": "YouBike2.0_MRT Jingmei Sta. (Exit 2)",
      "aren": "No. 1， Jingwen St. (Opposite)",
      "act": "1",
      "srcUpdateTime": "2025-04-20 00:31:20",
      "updateTime": "2025-04-20 00:31:26",
      "infoTime": "2025-04-19 22:42:14",
      "infoDate": "2025-04-19",
      "total": 63,
      "available_rent_bikes": 1,
      "latitude": 24.99366,
      "longitude": 121.54124,
      "available_return_bikes": 60
    }
  }
]